[
  { "code": "TWD", "symbol": "NT$", "nameZh": "新臺幣", "decimals": 0 },
  { "code": "JPY", "symbol": "¥", "nameZh": "日圓", "decimals": 0 },
  { "code": "KRW", "symbol": "₩", "nameZh": "韓元", "decimals": 0 },
  { "code": "THB", "symbol": "฿", "nameZh": "泰銖", "decimals": 2 },
  { "code": "USD", "symbol": "$", "nameZh": "美元", "decimals": 2 },
  { "code": "VND", "symbol": "₫", "nameZh": "越南盾", "decimals": 0 },
  { "code": "SGD", "symbol": "S$", "nameZh": "新加坡幣", "decimals": 2 },
  { "code": "GBP", "symbol": "£", "nameZh": "英鎊", "decimals": 2 },
  { "code": "EUR", "symbol": "€", "nameZh": "歐元", "decimals": 2 },
  { "code": "CNY", "symbol": "¥", "nameZh": "人民幣", "decimals": 2 },
  { "code": "HKD", "symbol": "HK$", "nameZh": "港幣", "decimals": 2 },
  { "code": "MYR", "symbol": "RM", "nameZh": "馬來西亞令吉", "decimals": 2 }
]
